cwcwidth-0.1.9.dist-info/LICENSE
cwcwidth-0.1.9.dist-info/top_level.txt
cwcwidth-0.1.9.dist-info/WHEEL
cwcwidth-0.1.9.dist-info/RECORD
cwcwidth-0.1.9.dist-info/METADATA
cwcwidth/_impl.pyi
cwcwidth/py.typed
cwcwidth/__init__.py
cwcwidth/_impl.cpython-310-i386-linux-gnu.so
