Metadata-Version: 2.1
Name: cwcwidth
Version: 0.1.9
Summary: Python bindings for wc(s)width
Home-page: https://github.com/sebastinas/cwcwidth
Author: Sebastian Ramacher
Author-email: sebastian@ramacher.at
License: MIT
Classifier: Development Status :: 5 - Production/Stable
Classifier: Intended Audience :: Developers
Classifier: License :: OSI Approved :: MIT License
Classifier: Programming Language :: Python :: 3
Classifier: Topic :: Software Development :: Libraries :: Python Modules
Requires-Python: >=3.8
License-File: LICENSE
